numtoolsfpat/__init__.py
tests/__init__.py
tests/test_numtools.py
numtoolsfpat-0.0.9.dist-info/METADATA
numtoolsfpat-0.0.9.dist-info/WHEEL
numtoolsfpat-0.0.9.dist-info/top_level.txt
numtoolsfpat-0.0.9.dist-info/RECORD
