Metadata-Version: 2.1
Name: numtoolsfpat
Version: 0.0.9
Summary: Number tools
Home-page: https://github.com/fptiangco/numtoolsfpat
Download-URL: https://github.com/fptiangco/numtoolsfpat
Project-URL: Bug Reports, https://github.com/fptiangco/numtoolsfpat/issues
Project-URL: Source, https://github.com/fptiangco/numtoolsfpat/
Keywords: numtoolsfpat
Classifier: License :: OSI Approved :: MIT License
Classifier: Intended Audience :: Developers
Classifier: Programming Language :: Python :: 3 :: Only
